sleepyjson/__init__.py
sleepyjson/node.py
sleepyjson/reader.py
sleepyjson-0.0.3.dist-info/LICENSE
sleepyjson-0.0.3.dist-info/METADATA
sleepyjson-0.0.3.dist-info/WHEEL
sleepyjson-0.0.3.dist-info/top_level.txt
sleepyjson-0.0.3.dist-info/RECORD
