Metadata-Version: 2.1
Name: sleepyjson
Version: 0.0.3
Summary: Read from JSON files without having to keep everything in memory
Home-page: https://github.com/jdferreira/sleepyjson
Author: João D. Ferreira
Author-email: jotomicron@gmail.com
License: UNKNOWN
Platform: UNKNOWN
Classifier: Programming Language :: Python :: 3
Classifier: License :: OSI Approved :: MIT License
Classifier: Operating System :: OS Independent
Requires-Python: >=3.6
